{
  "movie": {
    "tmdbId": 1315772,
    "imdbId": "tt32890033",
    "title": "Minions & Monsters",
    "originalTitle": "Minions & Monsters",
    "overview": "This is the rambunctious, ridiculous and totally true story of how the Minions conquered Hollywood, became movie stars, lost everything, unleashed monsters onto the world and then banded together to try and save the planet from the mayhem they had just created.",
    "releaseDate": "2026-06-24",
    "runtime": 90,
    "budget": "85000000",
    "revenue": "318467540",
    "status": "Released",
    "popularity": 286.1125,
    "voteAverage": 6.418,
    "voteCount": 194,
    "homepage": "https://www.minionsmovie.com",
    "posterPath": "/nz7i42yhLIJ4ve9JKgM6NthoLHO.jpg",
    "backdropPath": "/kkcwhgSFd81QDlXo8ytrpHPQjhy.jpg",
    "collectionId": 544669,
    "certification": "PG"
  },
  "collection": {
    "tmdbId": 544669,
    "name": "Minions Collection",
    "overview": null,
    "posterPath": "/lqU48HkuPDpbumwHk9syT7FbxpC.jpg",
    "backdropPath": "/62Qe28oi9PaK3P2ljDYUDTGAyST.jpg"
  },
  "genres": [
    {
      "tmdbId": 12,
      "name": "Adventure"
    },
    {
      "tmdbId": 16,
      "name": "Animation"
    },
    {
      "tmdbId": 35,
      "name": "Comedy"
    },
    {
      "tmdbId": 10751,
      "name": "Family"
    },
    {
      "tmdbId": 14,
      "name": "Fantasy"
    },
    {
      "tmdbId": 1,
      "name": "Drama"
    }
  ],
  "companies": [
    {
      "tmdbId": 33,
      "name": "Universal Pictures",
      "logoPath": "/8lvHyhjr8oUKOOy2dKXoALWKdp0.png",
      "originCountry": "US"
    },
    {
      "tmdbId": 6704,
      "name": "Illumination",
      "logoPath": "/fOG2oY4m1YuYTQh4bMqqZkmgOAI.png",
      "originCountry": "US"
    }
  ],
  "keywords": [],
  "videos": [
    {
      "name": "How did they do? See Jesse Eisenberg and Zoey Deutch in Minions and Monsters!",
      "key": "c0ALx7i34AM",
      "site": "YouTube",
      "size": 1080,
      "type": "Featurette"
    },
    {
      "name": "Minions co-creator Pierre Coffin on voicing the Minions and Minions & Monsters | BFI in Conversation",
      "key": "soGrC7190Vk",
      "site": "YouTube",
      "size": 1080,
      "type": "Featurette"
    },
    {
      "name": "IMAX Upgrade",
      "key": "4VqdHSN-Rss",
      "site": "YouTube",
      "size": 1080,
      "type": "Featurette"
    },
    {
      "name": "Everyone is going bananas for Minions and Monsters, don't miss it in cinemas now!",
      "key": "a_G7XFjggI8",
      "site": "YouTube",
      "size": 1080,
      "type": "Teaser"
    },
    {
      "name": "a moment of cinematic history",
      "key": "nbgs5KtzlfY",
      "site": "YouTube",
      "size": 1080,
      "type": "Featurette"
    },
    {
      "name": "you heard the man: the minions are back.",
      "key": "6LHjHY-WHL4",
      "site": "YouTube",
      "size": 1080,
      "type": "Teaser"
    },
    {
      "name": "How do we say 'all of the above' in Minionese? Let's go England!",
      "key": "aSxYl3qbN8Y",
      "site": "YouTube",
      "size": 1080,
      "type": "Teaser"
    },
    {
      "name": "This is not a drill... Minions and Monsters is in cinemas NOW!",
      "key": "RO5x9EecfKQ",
      "site": "YouTube",
      "size": 1080,
      "type": "Teaser"
    },
    {
      "name": "someone call HR....",
      "key": "ZL8uSKpctRM",
      "site": "YouTube",
      "size": 1080,
      "type": "Featurette"
    },
    {
      "name": "Why Minions Almost Ended After Despicable Me 3",
      "key": "eVzR0OcuUm4",
      "site": "YouTube",
      "size": 1080,
      "type": "Featurette"
    },
    {
      "name": "you never know who you'll run into at IMAX HQ",
      "key": "8X6vkR2xrS4",
      "site": "YouTube",
      "size": 1080,
      "type": "Featurette"
    },
    {
      "name": "More frightening than penalties",
      "key": "ySjj_Y5jfHY",
      "site": "YouTube",
      "size": 1080,
      "type": "Teaser"
    },
    {
      "name": "Behind the Score with John Powell",
      "key": "eYfBWBAaef4",
      "site": "YouTube",
      "size": 1080,
      "type": "Behind the Scenes"
    },
    {
      "name": "Bafana Bafana is through to the knockouts!",
      "key": "hTDpmUxTjFY",
      "site": "YouTube",
      "size": 1080,
      "type": "Featurette"
    },
    {
      "name": "If chaos was a movie... well...",
      "key": "D29E9wk0gEw",
      "site": "YouTube",
      "size": 1080,
      "type": "Teaser"
    },
    {
      "name": "Goomi Hears James' Movie Idea",
      "key": "7riKaZsk7dw",
      "site": "YouTube",
      "size": 1080,
      "type": "Clip"
    },
    {
      "name": "Get Tickets Now",
      "key": "6971-5yM0HY",
      "site": "YouTube",
      "size": 1080,
      "type": "Teaser"
    },
    {
      "name": "Extended Look",
      "key": "ihGBTI3nfCU",
      "site": "YouTube",
      "size": 1080,
      "type": "Clip"
    },
    {
      "name": "Shark Attack!",
      "key": "lO3PkZhI3_0",
      "site": "YouTube",
      "size": 1080,
      "type": "Clip"
    },
    {
      "name": "When worlds collide",
      "key": "tV1v5EfFc2g",
      "site": "YouTube",
      "size": 1080,
      "type": "Teaser"
    },
    {
      "name": "Look At Me",
      "key": "rd5cwf91WkU",
      "site": "YouTube",
      "size": 1080,
      "type": "Teaser"
    },
    {
      "name": "The Minions & Monsters Meal has landed at Wendy’s",
      "key": "wyUwsfmfuC8",
      "site": "YouTube",
      "size": 1080,
      "type": "Featurette"
    },
    {
      "name": "The Minions & Monsters Meal has landed at Wendy’s",
      "key": "Kp4WZlB_Lmo",
      "site": "YouTube",
      "size": 1080,
      "type": "Featurette"
    },
    {
      "name": "No brakes. Just vibes.",
      "key": "kyF-7P9kXQ8",
      "site": "YouTube",
      "size": 1080,
      "type": "Teaser"
    },
    {
      "name": "Minions 🤝 clowning around.",
      "key": "RXESlGpZABI",
      "site": "YouTube",
      "size": 1080,
      "type": "Teaser"
    },
    {
      "name": "Minions take a limo ride",
      "key": "MFFvtdDofjg",
      "site": "YouTube",
      "size": 1080,
      "type": "Clip"
    },
    {
      "name": "Goomi introduces himself to the Minions",
      "key": "DehHy1MYFcw",
      "site": "YouTube",
      "size": 1080,
      "type": "Clip"
    },
    {
      "name": "Only In Theaters July 1",
      "key": "v6wPfg6sksw",
      "site": "YouTube",
      "size": 1080,
      "type": "Teaser"
    },
    {
      "name": "Kylian Mbappe Enters The Match",
      "key": "eN11Sbg6Lsw",
      "site": "YouTube",
      "size": 1080,
      "type": "Featurette"
    },
    {
      "name": "Final Trailer",
      "key": "V-O-uBaHk3c",
      "site": "YouTube",
      "size": 2160,
      "type": "Trailer"
    },
    {
      "name": "Giannis Antetokounmpo Goes Hollywood",
      "key": "nA2xmEfg4Xk",
      "site": "YouTube",
      "size": 1080,
      "type": "Featurette"
    },
    {
      "name": "Official Cast Announcement",
      "key": "UaH6fShfpuY",
      "site": "YouTube",
      "size": 1080,
      "type": "Teaser"
    },
    {
      "name": "Big Game Spot",
      "key": "EVLrnh2Hj8I",
      "site": "YouTube",
      "size": 2160,
      "type": "Teaser"
    },
    {
      "name": "Official Trailer",
      "key": "ZSdOwt-G49w",
      "site": "YouTube",
      "size": 2160,
      "type": "Trailer"
    }
  ],
  "images": [
    {
      "filePath": "/nz7i42yhLIJ4ve9JKgM6NthoLHO.jpg",
      "width": null,
      "height": null,
      "aspectRatio": null,
      "type": "poster"
    },
    {
      "filePath": "/kkcwhgSFd81QDlXo8ytrpHPQjhy.jpg",
      "width": null,
      "height": null,
      "aspectRatio": null,
      "type": "backdrop"
    },
    {
      "filePath": "/hTowtXrkCY7FJyoj4p91JckrJSE.jpg",
      "width": 2000,
      "height": 3000,
      "aspectRatio": 0.667,
      "type": "poster"
    },
    {
      "filePath": "/nz7i42yhLIJ4ve9JKgM6NthoLHO.jpg",
      "width": 2000,
      "height": 3000,
      "aspectRatio": 0.667,
      "type": "poster"
    },
    {
      "filePath": "/vrTlRYPhnf107vbTiDf6DRrdV3r.jpg",
      "width": 2000,
      "height": 3000,
      "aspectRatio": 0.667,
      "type": "poster"
    },
    {
      "filePath": "/uUWVnwFvEWpOIGpWrwcnw5gVvzq.jpg",
      "width": 2000,
      "height": 3000,
      "aspectRatio": 0.667,
      "type": "poster"
    },
    {
      "filePath": "/sO3O1szSYuXLwtkobU5TExQ6Wfa.jpg",
      "width": 2000,
      "height": 3000,
      "aspectRatio": 0.667,
      "type": "poster"
    },
    {
      "filePath": "/9THY3T4kn5D2rZhwwQ6t7XQtHtv.jpg",
      "width": 1080,
      "height": 1440,
      "aspectRatio": 0.75,
      "type": "poster"
    },
    {
      "filePath": "/5Bu0nKJxTQd2bVUDF9qrpEEFt1a.jpg",
      "width": 2000,
      "height": 3000,
      "aspectRatio": 0.667,
      "type": "poster"
    },
    {
      "filePath": "/hNXw1I4GmLCbSdbnduoR7SVY8Jv.jpg",
      "width": 1365,
      "height": 2048,
      "aspectRatio": 0.667,
      "type": "poster"
    },
    {
      "filePath": "/z8OWDTR7pQuZi7jkEuR7yMXRrQt.jpg",
      "width": 1000,
      "height": 1500,
      "aspectRatio": 0.667,
      "type": "poster"
    },
    {
      "filePath": "/lfASk37BOkRWDxwlm5noCyxaU26.jpg",
      "width": 1000,
      "height": 1482,
      "aspectRatio": 0.675,
      "type": "poster"
    },
    {
      "filePath": "/u75I7gCM59Ni7MkYNZ3HBUS5l5h.jpg",
      "width": 2000,
      "height": 3000,
      "aspectRatio": 0.667,
      "type": "poster"
    },
    {
      "filePath": "/mEWHWviImg9A509t7eOAUOBc01Q.jpg",
      "width": 2000,
      "height": 3000,
      "aspectRatio": 0.667,
      "type": "poster"
    },
    {
      "filePath": "/9kq7OhATacbR7dDr46tHd42WcIP.jpg",
      "width": 2000,
      "height": 3000,
      "aspectRatio": 0.667,
      "type": "poster"
    },
    {
      "filePath": "/iWFRBbTCUX1FfGgMsWCTxC31YuK.jpg",
      "width": 1000,
      "height": 1500,
      "aspectRatio": 0.667,
      "type": "poster"
    },
    {
      "filePath": "/yLYdUmUc7BV8g5UaGFwuGSRUZKt.jpg",
      "width": 2000,
      "height": 3000,
      "aspectRatio": 0.667,
      "type": "poster"
    },
    {
      "filePath": "/sAc6kDXmIj8mYe98re4N8o3mlmp.jpg",
      "width": 2000,
      "height": 3000,
      "aspectRatio": 0.667,
      "type": "poster"
    },
    {
      "filePath": "/6jtBUoqgOSElz1v5QahkrWCYXm1.jpg",
      "width": 990,
      "height": 1400,
      "aspectRatio": 0.707,
      "type": "poster"
    },
    {
      "filePath": "/bv1V6it35HKWn81nBsL5I9lyLgk.jpg",
      "width": 2000,
      "height": 3000,
      "aspectRatio": 0.667,
      "type": "poster"
    },
    {
      "filePath": "/apSlz7nZP0wgFPE93cOooBaolxm.jpg",
      "width": 2000,
      "height": 3000,
      "aspectRatio": 0.667,
      "type": "poster"
    },
    {
      "filePath": "/n5erezuDJO5ieLnXwAwipi7P6aG.jpg",
      "width": 2000,
      "height": 3000,
      "aspectRatio": 0.667,
      "type": "poster"
    },
    {
      "filePath": "/2SrLYoNupmaTJlv2NnXV9ZG9Nki.jpg",
      "width": 2000,
      "height": 3000,
      "aspectRatio": 0.667,
      "type": "poster"
    },
    {
      "filePath": "/sTQpzcwBXnYNRipgnhwL7EHHW74.jpg",
      "width": 2000,
      "height": 3000,
      "aspectRatio": 0.667,
      "type": "poster"
    },
    {
      "filePath": "/uV0zglmSP42bv45dfaQg37ws6pM.jpg",
      "width": 2000,
      "height": 2815,
      "aspectRatio": 0.71,
      "type": "poster"
    },
    {
      "filePath": "/8wYHlLEIrEKvbfj83B11g7FKFd8.jpg",
      "width": 2000,
      "height": 3000,
      "aspectRatio": 0.667,
      "type": "poster"
    },
    {
      "filePath": "/jMOf0SSthlNp5uXhEXz4e3tqDX5.jpg",
      "width": 2000,
      "height": 3000,
      "aspectRatio": 0.667,
      "type": "poster"
    },
    {
      "filePath": "/AoaoPbO7434LeDB2EI11JJy7b9F.jpg",
      "width": 2000,
      "height": 3000,
      "aspectRatio": 0.667,
      "type": "poster"
    },
    {
      "filePath": "/extFlxIXpABjsmKCVktlzklgCxL.jpg",
      "width": 1080,
      "height": 1600,
      "aspectRatio": 0.675,
      "type": "poster"
    },
    {
      "filePath": "/yBTbcTpxN7jzDM3SyGgzVUH1pOk.jpg",
      "width": 2000,
      "height": 3000,
      "aspectRatio": 0.667,
      "type": "poster"
    },
    {
      "filePath": "/s2IruLQG6577vX9SBMhuoEqK4WF.jpg",
      "width": 2000,
      "height": 3000,
      "aspectRatio": 0.667,
      "type": "poster"
    },
    {
      "filePath": "/voJFdRJ4KufQg4KPcO9EkgCV3Z4.jpg",
      "width": 2000,
      "height": 3000,
      "aspectRatio": 0.667,
      "type": "poster"
    },
    {
      "filePath": "/y4JWxHZ1dMisqbHhX7ytOAK3wwv.jpg",
      "width": 2000,
      "height": 3000,
      "aspectRatio": 0.667,
      "type": "poster"
    },
    {
      "filePath": "/4LjkiYcV8p2aACZYayge5LaR4vS.jpg",
      "width": 600,
      "height": 900,
      "aspectRatio": 0.667,
      "type": "poster"
    },
    {
      "filePath": "/sqGwjpxqjlIYToP3LkEyNACEI7m.jpg",
      "width": 2000,
      "height": 3000,
      "aspectRatio": 0.667,
      "type": "poster"
    },
    {
      "filePath": "/gKTp55PtWGa6rxwwmNUeJwZ6qDj.jpg",
      "width": 2000,
      "height": 3000,
      "aspectRatio": 0.667,
      "type": "poster"
    },
    {
      "filePath": "/8fVbtDLdO0ZMrnZ51CC4a604AJ0.jpg",
      "width": 2000,
      "height": 3000,
      "aspectRatio": 0.667,
      "type": "poster"
    },
    {
      "filePath": "/hPWctCY0B64pYJaKXj7S22kYcEM.jpg",
      "width": 2000,
      "height": 3000,
      "aspectRatio": 0.667,
      "type": "poster"
    },
    {
      "filePath": "/yqwWryJmIY63ONbWyoKVBFGltoZ.jpg",
      "width": 2000,
      "height": 3000,
      "aspectRatio": 0.667,
      "type": "poster"
    },
    {
      "filePath": "/fNs35oLUYWGrqgCJvaUthsHjpTN.jpg",
      "width": 800,
      "height": 1126,
      "aspectRatio": 0.71,
      "type": "poster"
    },
    {
      "filePath": "/hu7Gq6cgQiRUAPz76ZuJ2eZDncj.jpg",
      "width": 2000,
      "height": 3000,
      "aspectRatio": 0.667,
      "type": "poster"
    },
    {
      "filePath": "/5DqFrolm5bgxCIOjzqDPTrde2fu.jpg",
      "width": 2000,
      "height": 3000,
      "aspectRatio": 0.667,
      "type": "poster"
    },
    {
      "filePath": "/5fbA0Ct8eZmJfQKJLyJ7uAQuhbS.jpg",
      "width": 2000,
      "height": 3000,
      "aspectRatio": 0.667,
      "type": "poster"
    },
    {
      "filePath": "/1f7F27dEZ79ZCZZukEyr2GPKP5a.jpg",
      "width": 2000,
      "height": 3000,
      "aspectRatio": 0.667,
      "type": "poster"
    },
    {
      "filePath": "/lEJnQIUaeUEBAWJ5LOApXDUE7ze.jpg",
      "width": 2000,
      "height": 3000,
      "aspectRatio": 0.667,
      "type": "poster"
    },
    {
      "filePath": "/ttSHXoTrLtRgrWucLwlVhTdTe3L.jpg",
      "width": 2000,
      "height": 3000,
      "aspectRatio": 0.667,
      "type": "poster"
    },
    {
      "filePath": "/yjnFvABowRDHNjfLImVVW3CdQPU.jpg",
      "width": 1364,
      "height": 2048,
      "aspectRatio": 0.666,
      "type": "poster"
    },
    {
      "filePath": "/prDTGLRRxp1T1f3910mRjBxWdeS.jpg",
      "width": 2000,
      "height": 3000,
      "aspectRatio": 0.667,
      "type": "poster"
    },
    {
      "filePath": "/upPa99ttYOuiJQyqvg1ukPbqHCS.jpg",
      "width": 2000,
      "height": 3000,
      "aspectRatio": 0.667,
      "type": "poster"
    },
    {
      "filePath": "/iq8ZhE81WmPRIXqc6f7FjeGCN2s.jpg",
      "width": 533,
      "height": 800,
      "aspectRatio": 0.666,
      "type": "poster"
    },
    {
      "filePath": "/qCqaJRGyx8fz22VHdAZ4GX7DOE.jpg",
      "width": 2000,
      "height": 3000,
      "aspectRatio": 0.667,
      "type": "poster"
    },
    {
      "filePath": "/hozvAwffDtJ9kXGlGvs57B2GZfh.jpg",
      "width": 2000,
      "height": 3000,
      "aspectRatio": 0.667,
      "type": "poster"
    },
    {
      "filePath": "/34PSt8YXqI3ujGXiDZUIWHbFMNw.jpg",
      "width": 2000,
      "height": 3000,
      "aspectRatio": 0.667,
      "type": "poster"
    },
    {
      "filePath": "/mU5C9b3AiduvEf7sypYjlgFMEYh.jpg",
      "width": 900,
      "height": 1350,
      "aspectRatio": 0.667,
      "type": "poster"
    },
    {
      "filePath": "/2j0B3SusWJGsM2gD0Riy47juAAf.jpg",
      "width": 2000,
      "height": 3000,
      "aspectRatio": 0.667,
      "type": "poster"
    },
    {
      "filePath": "/rtlkXYlciC396qleYDRln0WggZ8.jpg",
      "width": 1579,
      "height": 2368,
      "aspectRatio": 0.667,
      "type": "poster"
    },
    {
      "filePath": "/d31KC9giCW3PQURS43OGGucimDJ.jpg",
      "width": 1769,
      "height": 2653,
      "aspectRatio": 0.667,
      "type": "poster"
    },
    {
      "filePath": "/eQTpJShjwJ5zbYWjb468Jke7n6J.jpg",
      "width": 500,
      "height": 750,
      "aspectRatio": 0.667,
      "type": "poster"
    },
    {
      "filePath": "/8p75H5AHWWETuHa1PLTGwNkhbFm.jpg",
      "width": 2000,
      "height": 3000,
      "aspectRatio": 0.667,
      "type": "poster"
    },
    {
      "filePath": "/xCHUdBfHUoRMDKBCqAjH3C4PyEm.jpg",
      "width": 1950,
      "height": 2925,
      "aspectRatio": 0.667,
      "type": "poster"
    },
    {
      "filePath": "/mlBo39TLofd1sIDtg0F6fxghvyR.jpg",
      "width": 1536,
      "height": 2048,
      "aspectRatio": 0.75,
      "type": "poster"
    },
    {
      "filePath": "/xu1BxixGkLDPkUzu0MMxR3K2GaQ.jpg",
      "width": 1050,
      "height": 1551,
      "aspectRatio": 0.677,
      "type": "poster"
    },
    {
      "filePath": "/jBpjzbukgU7M0k5hKuS9xi5aoVG.jpg",
      "width": 1257,
      "height": 1885,
      "aspectRatio": 0.667,
      "type": "poster"
    },
    {
      "filePath": "/vBmZXj27wDKqQnHOKfu0tHXB5A7.jpg",
      "width": 1257,
      "height": 1885,
      "aspectRatio": 0.667,
      "type": "poster"
    },
    {
      "filePath": "/dIQsGbXFpxKmya1EWdAXnRGsnvm.jpg",
      "width": 1536,
      "height": 2048,
      "aspectRatio": 0.75,
      "type": "poster"
    },
    {
      "filePath": "/822dQlRkYV5X23WGdxEZGVxKpa9.jpg",
      "width": 1769,
      "height": 2653,
      "aspectRatio": 0.667,
      "type": "poster"
    },
    {
      "filePath": "/5pMalhUiKXcRuZQ3MdWt9QRAkcI.jpg",
      "width": 900,
      "height": 1350,
      "aspectRatio": 0.667,
      "type": "poster"
    },
    {
      "filePath": "/82NUiVdEGhCzmE2un9HXGPGkCEV.jpg",
      "width": 2000,
      "height": 3000,
      "aspectRatio": 0.667,
      "type": "poster"
    },
    {
      "filePath": "/igD0dUmeaJfWME9j3OoqeN2dHvp.jpg",
      "width": 810,
      "height": 1080,
      "aspectRatio": 0.75,
      "type": "poster"
    },
    {
      "filePath": "/sp0DnOTVKLeelttj7s1mqzFrwSP.jpg",
      "width": 2000,
      "height": 3000,
      "aspectRatio": 0.667,
      "type": "poster"
    },
    {
      "filePath": "/1JqyiXnKnvbGyYuG1bYQrPbRuZs.jpg",
      "width": 1999,
      "height": 3000,
      "aspectRatio": 0.666,
      "type": "poster"
    },
    {
      "filePath": "/gntlEQ6F3q6wAXiqshNJ0Gct2F6.jpg",
      "width": 2000,
      "height": 3000,
      "aspectRatio": 0.667,
      "type": "poster"
    },
    {
      "filePath": "/lvrUysmbrudVP2fqtlRejIg9KFZ.jpg",
      "width": 1365,
      "height": 2048,
      "aspectRatio": 0.667,
      "type": "poster"
    },
    {
      "filePath": "/vJHa85i6ZOZIvcPK0ak4nSpijZv.jpg",
      "width": 1000,
      "height": 1500,
      "aspectRatio": 0.667,
      "type": "poster"
    },
    {
      "filePath": "/19u0Dd3flmNq988YZPV4tUZgD9k.jpg",
      "width": 2000,
      "height": 3000,
      "aspectRatio": 0.667,
      "type": "poster"
    },
    {
      "filePath": "/xLYNZRahk79EYEHLaz9rwZWczp1.jpg",
      "width": 1000,
      "height": 1500,
      "aspectRatio": 0.667,
      "type": "poster"
    },
    {
      "filePath": "/oOrFCTI8v9fHe6fF9uXQciH6OIE.jpg",
      "width": 1000,
      "height": 1500,
      "aspectRatio": 0.667,
      "type": "poster"
    },
    {
      "filePath": "/v5UvIovhkESnC2qJg5DK5jALzdr.jpg",
      "width": 1440,
      "height": 2160,
      "aspectRatio": 0.667,
      "type": "poster"
    },
    {
      "filePath": "/nOxeKXxqi1InjYnXmBIA6gHjtEA.jpg",
      "width": 2000,
      "height": 3000,
      "aspectRatio": 0.667,
      "type": "poster"
    },
    {
      "filePath": "/nfacmeT2xbAbZE0PNjqDTzGUiZ.jpg",
      "width": 1379,
      "height": 2068,
      "aspectRatio": 0.667,
      "type": "poster"
    },
    {
      "filePath": "/eI5fG9m5ibWsV5MgxtyhYC9NkSs.jpg",
      "width": 2000,
      "height": 3000,
      "aspectRatio": 0.667,
      "type": "poster"
    },
    {
      "filePath": "/uAjijW9NhqIkxbGEt2T0gJkCADW.jpg",
      "width": 2000,
      "height": 3000,
      "aspectRatio": 0.667,
      "type": "poster"
    },
    {
      "filePath": "/otwAr7eaJpdhTf76zfkbp6TWM51.jpg",
      "width": 719,
      "height": 1078,
      "aspectRatio": 0.667,
      "type": "poster"
    },
    {
      "filePath": "/b3jzbShrL534gEb0cep9ypBKkH1.jpg",
      "width": 2000,
      "height": 3000,
      "aspectRatio": 0.667,
      "type": "poster"
    },
    {
      "filePath": "/gPnytUsFNFH3sbZ8v3Pc3qO2iv8.jpg",
      "width": 900,
      "height": 1350,
      "aspectRatio": 0.667,
      "type": "poster"
    },
    {
      "filePath": "/usaG69dFW2iiOPIdvFL3YiO3pzN.jpg",
      "width": 2000,
      "height": 3000,
      "aspectRatio": 0.667,
      "type": "poster"
    },
    {
      "filePath": "/4RRGjHlhCJAU8vkJwzYd2bH9IkL.jpg",
      "width": 2000,
      "height": 3000,
      "aspectRatio": 0.667,
      "type": "poster"
    },
    {
      "filePath": "/8uvgppq5obV06X9X8SogQiU79Kd.jpg",
      "width": 1263,
      "height": 1895,
      "aspectRatio": 0.666,
      "type": "poster"
    },
    {
      "filePath": "/ul0dWExN1UXn5ktN7x4KKp5ISNr.jpg",
      "width": 900,
      "height": 1350,
      "aspectRatio": 0.667,
      "type": "poster"
    },
    {
      "filePath": "/amfpWj77Z8x5O76G2EhjquJqzoi.jpg",
      "width": 1000,
      "height": 1499,
      "aspectRatio": 0.667,
      "type": "poster"
    },
    {
      "filePath": "/pSJlbJGPwt5LZdj3DzFGOnzO8Zq.jpg",
      "width": 1769,
      "height": 2653,
      "aspectRatio": 0.667,
      "type": "poster"
    },
    {
      "filePath": "/hmEuXMDUHWQYJLFJI6oGEPi4gBa.jpg",
      "width": 2000,
      "height": 3000,
      "aspectRatio": 0.667,
      "type": "poster"
    },
    {
      "filePath": "/c0mC0cEIoAlFqZwZjhO24eUDkqs.jpg",
      "width": 2000,
      "height": 3000,
      "aspectRatio": 0.667,
      "type": "poster"
    },
    {
      "filePath": "/xznlWTLMD91sJEkqZi1wExnlFdo.jpg",
      "width": 2000,
      "height": 3000,
      "aspectRatio": 0.667,
      "type": "poster"
    },
    {
      "filePath": "/5jAA59Xo7xGByoVKUCymGGOKIX4.jpg",
      "width": 2000,
      "height": 3000,
      "aspectRatio": 0.667,
      "type": "poster"
    },
    {
      "filePath": "/ai10GoujvMbpWtXWvW0aPqxrDNm.jpg",
      "width": 1294,
      "height": 1941,
      "aspectRatio": 0.667,
      "type": "poster"
    },
    {
      "filePath": "/j7zyxpMi5mc3Ym1UEGAutrGkqru.jpg",
      "width": 1616,
      "height": 2424,
      "aspectRatio": 0.667,
      "type": "poster"
    },
    {
      "filePath": "/kuVqoYoUnlL9OLhGfobqMRYxVIT.jpg",
      "width": 2000,
      "height": 3000,
      "aspectRatio": 0.667,
      "type": "poster"
    },
    {
      "filePath": "/qfnYICA2zTIaj3sOBGtNu2KAmpt.jpg",
      "width": 2000,
      "height": 3000,
      "aspectRatio": 0.667,
      "type": "poster"
    },
    {
      "filePath": "/z9oCkT0O3BTnHsCKdxV8ORPg3Ij.jpg",
      "width": 2000,
      "height": 3000,
      "aspectRatio": 0.667,
      "type": "poster"
    },
    {
      "filePath": "/uYs4IJdDQvnrNvVtYBNmjiHqbmF.jpg",
      "width": 2000,
      "height": 3000,
      "aspectRatio": 0.667,
      "type": "poster"
    },
    {
      "filePath": "/95GBatkxCjqmYYX3r9v4EoKM7ay.jpg",
      "width": 2000,
      "height": 3000,
      "aspectRatio": 0.667,
      "type": "poster"
    },
    {
      "filePath": "/o9cqVLit37NNr8ZSPUJ2bTMcyCe.jpg",
      "width": 530,
      "height": 750,
      "aspectRatio": 0.707,
      "type": "poster"
    },
    {
      "filePath": "/k7V4axHCP0BeZojW0lxnZWnYM2l.jpg",
      "width": 2000,
      "height": 3000,
      "aspectRatio": 0.667,
      "type": "poster"
    },
    {
      "filePath": "/vNh4nW7GDVjVN63kY5NVSAWBWMO.jpg",
      "width": 1950,
      "height": 2925,
      "aspectRatio": 0.667,
      "type": "poster"
    },
    {
      "filePath": "/6PGxaXBpXGjw1mPl6TntTiNx1Kj.jpg",
      "width": 900,
      "height": 1350,
      "aspectRatio": 0.667,
      "type": "poster"
    },
    {
      "filePath": "/8c081VoUfhM7cfblZ8nTPRCMBgc.jpg",
      "width": 1365,
      "height": 2048,
      "aspectRatio": 0.667,
      "type": "poster"
    },
    {
      "filePath": "/hpoa7nE8pXz5RT4S4dOJktnNl0h.jpg",
      "width": 1365,
      "height": 2048,
      "aspectRatio": 0.667,
      "type": "poster"
    },
    {
      "filePath": "/6Sfeinn2dMF2Bk4OeOlULu8zA8i.jpg",
      "width": 1365,
      "height": 2048,
      "aspectRatio": 0.667,
      "type": "poster"
    },
    {
      "filePath": "/nsa5m7mbXKa69ZNsj4QFFT9eddc.jpg",
      "width": 1365,
      "height": 2048,
      "aspectRatio": 0.667,
      "type": "poster"
    },
    {
      "filePath": "/tYbjDzGxSVNOTxeiTSEZx4pf6uz.jpg",
      "width": 1365,
      "height": 2048,
      "aspectRatio": 0.667,
      "type": "poster"
    },
    {
      "filePath": "/92iI5mfaIU6wdQnDI4ThhzFW1eN.jpg",
      "width": 2000,
      "height": 3000,
      "aspectRatio": 0.667,
      "type": "poster"
    },
    {
      "filePath": "/rq3d2jka4qrBOVqNGhbU7lrzGF8.jpg",
      "width": 1440,
      "height": 2160,
      "aspectRatio": 0.667,
      "type": "poster"
    },
    {
      "filePath": "/aZZOhVBebGkFdi7KSAasaAkK7BV.jpg",
      "width": 2000,
      "height": 3000,
      "aspectRatio": 0.667,
      "type": "poster"
    },
    {
      "filePath": "/ymsYkCrWHShPCYhUc8WjGJcUzxe.jpg",
      "width": 2000,
      "height": 3000,
      "aspectRatio": 0.667,
      "type": "poster"
    },
    {
      "filePath": "/8iv4G0WUscbEDeoOs3d099KuWOQ.jpg",
      "width": 2000,
      "height": 3000,
      "aspectRatio": 0.667,
      "type": "poster"
    },
    {
      "filePath": "/wdNo9GklzUoyKHDe0sYmKDAYSZN.jpg",
      "width": 2000,
      "height": 3000,
      "aspectRatio": 0.667,
      "type": "poster"
    },
    {
      "filePath": "/ugIV59N98sTLTS00n2edz2YUSrH.jpg",
      "width": 1000,
      "height": 1500,
      "aspectRatio": 0.667,
      "type": "poster"
    },
    {
      "filePath": "/opsdDHqtB6c5pSjo536x6njnXlc.jpg",
      "width": 900,
      "height": 1350,
      "aspectRatio": 0.667,
      "type": "poster"
    },
    {
      "filePath": "/6H2ylkdpQlKBduA1CgLSF5bT3VK.jpg",
      "width": 2000,
      "height": 3000,
      "aspectRatio": 0.667,
      "type": "poster"
    },
    {
      "filePath": "/4gaxjT4TlrIDI9bJFwRMQI1KSFp.jpg",
      "width": 2000,
      "height": 3000,
      "aspectRatio": 0.667,
      "type": "poster"
    },
    {
      "filePath": "/7DUzo8Ys7BfmZpqnzIwG4qA0egl.jpg",
      "width": 2000,
      "height": 3000,
      "aspectRatio": 0.667,
      "type": "poster"
    },
    {
      "filePath": "/kNmyLjdYJB1OyqmQXian4H8wqWn.jpg",
      "width": 800,
      "height": 1200,
      "aspectRatio": 0.667,
      "type": "poster"
    },
    {
      "filePath": "/7e7tlV6wSPbHersXYx5i3TnLrHp.jpg",
      "width": 1050,
      "height": 1551,
      "aspectRatio": 0.677,
      "type": "poster"
    },
    {
      "filePath": "/11YRubYZy9rEmxt3MsJ6CD2Q5dr.jpg",
      "width": 753,
      "height": 1130,
      "aspectRatio": 0.666,
      "type": "poster"
    },
    {
      "filePath": "/oGYOtoigoVApMUxzyoMq2rUM04z.jpg",
      "width": 1013,
      "height": 1350,
      "aspectRatio": 0.75,
      "type": "poster"
    },
    {
      "filePath": "/jsHdJwA5TgX9ylldbTJnxFpdUBo.jpg",
      "width": 800,
      "height": 1126,
      "aspectRatio": 0.71,
      "type": "poster"
    },
    {
      "filePath": "/zohLb7x4Q72t91YfOXYZbNO2c8K.jpg",
      "width": 2000,
      "height": 3000,
      "aspectRatio": 0.667,
      "type": "poster"
    },
    {
      "filePath": "/sBIhcY8uZV0nwsoCGSRt3ZEdX8T.jpg",
      "width": 901,
      "height": 1350,
      "aspectRatio": 0.667,
      "type": "poster"
    },
    {
      "filePath": "/Ar3jbZILenImlviaB0fGqrCp118.jpg",
      "width": 901,
      "height": 1350,
      "aspectRatio": 0.667,
      "type": "poster"
    },
    {
      "filePath": "/gx71Cd7ViFClYNMkruj6h1n4j9Q.jpg",
      "width": 2000,
      "height": 3000,
      "aspectRatio": 0.667,
      "type": "poster"
    },
    {
      "filePath": "/9cEJxLkWyxj4fosRYWDvTVDvfuc.jpg",
      "width": 1000,
      "height": 1500,
      "aspectRatio": 0.667,
      "type": "poster"
    },
    {
      "filePath": "/amsdMH66C4CNcx7evFT37cIwHV7.jpg",
      "width": 2000,
      "height": 3000,
      "aspectRatio": 0.667,
      "type": "poster"
    },
    {
      "filePath": "/hhG3fjXyBso5bMJF4XpXm76IaxX.jpg",
      "width": 1991,
      "height": 3000,
      "aspectRatio": 0.664,
      "type": "poster"
    },
    {
      "filePath": "/lpsnOXk0FgdhtljP7TAfDp3QvVT.jpg",
      "width": 1620,
      "height": 2400,
      "aspectRatio": 0.675,
      "type": "poster"
    },
    {
      "filePath": "/71aciHrNFqRwLvqg24qmt5CHerx.jpg",
      "width": 2000,
      "height": 2963,
      "aspectRatio": 0.675,
      "type": "poster"
    },
    {
      "filePath": "/blRlkbKodb4N8pkh9ZyMFSbKFBr.jpg",
      "width": 1620,
      "height": 2400,
      "aspectRatio": 0.675,
      "type": "poster"
    },
    {
      "filePath": "/v8mt8w5nvVOhFwLGtc0OO6OHIuC.jpg",
      "width": 1364,
      "height": 2048,
      "aspectRatio": 0.666,
      "type": "poster"
    },
    {
      "filePath": "/jvt72nXIjFdrO9vMom0jduqCvte.jpg",
      "width": 1280,
      "height": 1897,
      "aspectRatio": 0.675,
      "type": "poster"
    },
    {
      "filePath": "/he9uiCzgirelkjdq96BBmI0OAMJ.jpg",
      "width": 1923,
      "height": 2849,
      "aspectRatio": 0.675,
      "type": "poster"
    },
    {
      "filePath": "/8CUXXI1z7oRCDGFtWYhpSDpSmdu.jpg",
      "width": 1280,
      "height": 1896,
      "aspectRatio": 0.675,
      "type": "poster"
    },
    {
      "filePath": "/teJrCb3OLfDWS06grVAesLbJr0r.jpg",
      "width": 1365,
      "height": 2048,
      "aspectRatio": 0.667,
      "type": "poster"
    },
    {
      "filePath": "/fv30LRC6oLlgVwtIUzWbNwmiiEv.jpg",
      "width": 960,
      "height": 1440,
      "aspectRatio": 0.667,
      "type": "poster"
    },
    {
      "filePath": "/v8eZDaWi4wQpjdI56teElpJK3fo.jpg",
      "width": 800,
      "height": 1200,
      "aspectRatio": 0.667,
      "type": "poster"
    },
    {
      "filePath": "/fk2PAwpSJiFqYpkSOV7G1T3ZEmX.jpg",
      "width": 2000,
      "height": 3000,
      "aspectRatio": 0.667,
      "type": "poster"
    },
    {
      "filePath": "/7ua23ZpwltQLuEsLh7LPJ1x9LGf.jpg",
      "width": 2000,
      "height": 3000,
      "aspectRatio": 0.667,
      "type": "poster"
    },
    {
      "filePath": "/tP68HcR6fBSentCgMKrSjjm0k4T.jpg",
      "width": 2000,
      "height": 3000,
      "aspectRatio": 0.667,
      "type": "poster"
    },
    {
      "filePath": "/gUR9XHdzI4iy6w79VmF8XRYVVbh.jpg",
      "width": 2000,
      "height": 3000,
      "aspectRatio": 0.667,
      "type": "poster"
    },
    {
      "filePath": "/oVArKGqt6QotQmt0NpFtlVS4XC8.jpg",
      "width": 2000,
      "height": 3000,
      "aspectRatio": 0.667,
      "type": "poster"
    },
    {
      "filePath": "/1vBhAcY4yAyGWf69a5OVlU6oyrz.jpg",
      "width": 2000,
      "height": 3000,
      "aspectRatio": 0.667,
      "type": "poster"
    },
    {
      "filePath": "/bPPoo0VKdPNfWFYGj7qhYdXpSuv.jpg",
      "width": 2000,
      "height": 3000,
      "aspectRatio": 0.667,
      "type": "poster"
    },
    {
      "filePath": "/quUdF9ZnyuvVxZKzFzOw3gqVCXG.jpg",
      "width": 2000,
      "height": 3000,
      "aspectRatio": 0.667,
      "type": "poster"
    },
    {
      "filePath": "/5ToVmqa7ygcb6DYrvRF4ygKC2i6.jpg",
      "width": 2000,
      "height": 3000,
      "aspectRatio": 0.667,
      "type": "poster"
    },
    {
      "filePath": "/d4AabDpVcJD9B153dxZUogOee1i.jpg",
      "width": 2000,
      "height": 3000,
      "aspectRatio": 0.667,
      "type": "poster"
    },
    {
      "filePath": "/gskACY1qlUCaBpC1M7ATj8DSi63.jpg",
      "width": 2000,
      "height": 3000,
      "aspectRatio": 0.667,
      "type": "poster"
    },
    {
      "filePath": "/6WxnAdaTmFIsV4il2L2thh375sk.jpg",
      "width": 2000,
      "height": 3000,
      "aspectRatio": 0.667,
      "type": "poster"
    },
    {
      "filePath": "/baQkDbcmLTTKFh2g6VsGhRkAqEv.jpg",
      "width": 2000,
      "height": 3000,
      "aspectRatio": 0.667,
      "type": "poster"
    },
    {
      "filePath": "/5duWLRjzhjjnb2wgQodKT6RnI7C.jpg",
      "width": 2000,
      "height": 3000,
      "aspectRatio": 0.667,
      "type": "poster"
    },
    {
      "filePath": "/tHvvsLMZjMRZ4NxWxwz9Nk5GfYG.jpg",
      "width": 2000,
      "height": 3000,
      "aspectRatio": 0.667,
      "type": "poster"
    },
    {
      "filePath": "/cPBSMDSDSInW3dnBUIfZg5W5lIg.jpg",
      "width": 2000,
      "height": 3000,
      "aspectRatio": 0.667,
      "type": "poster"
    },
    {
      "filePath": "/8FXkOxXmCwjafIbzXKAPPlQtSxO.jpg",
      "width": 2000,
      "height": 3000,
      "aspectRatio": 0.667,
      "type": "poster"
    },
    {
      "filePath": "/wb3u6T9vibjtAmevll50lQJOUVZ.jpg",
      "width": 2000,
      "height": 3000,
      "aspectRatio": 0.667,
      "type": "poster"
    },
    {
      "filePath": "/ckYHeM3YGh9iyZcY5kmnYlAJPF6.jpg",
      "width": 2000,
      "height": 3000,
      "aspectRatio": 0.667,
      "type": "poster"
    },
    {
      "filePath": "/cKEey7JxT39rn4HJ2dIKD0MnReX.jpg",
      "width": 1379,
      "height": 2068,
      "aspectRatio": 0.667,
      "type": "poster"
    },
    {
      "filePath": "/A4fttEogsqHwA1AJmDwfLXQTe0I.jpg",
      "width": 2000,
      "height": 3000,
      "aspectRatio": 0.667,
      "type": "poster"
    },
    {
      "filePath": "/wxJAx4hNG958ViVeqz1dKkerZpM.jpg",
      "width": 2000,
      "height": 2830,
      "aspectRatio": 0.707,
      "type": "poster"
    },
    {
      "filePath": "/1E8iDlvkW9EIgkTAJFvVCL5bf26.jpg",
      "width": 1376,
      "height": 1948,
      "aspectRatio": 0.706,
      "type": "poster"
    },
    {
      "filePath": "/lv7Mv0b89ksaR4vRU0Cj3SDSx4r.jpg",
      "width": 1447,
      "height": 2048,
      "aspectRatio": 0.707,
      "type": "poster"
    },
    {
      "filePath": "/7zukPZ1IV2h83fMOl0s52UYCPuL.jpg",
      "width": 1000,
      "height": 1500,
      "aspectRatio": 0.667,
      "type": "poster"
    },
    {
      "filePath": "/glzOv4Vzr6ZHP0ToHqLakF5fkfk.jpg",
      "width": 2000,
      "height": 3000,
      "aspectRatio": 0.667,
      "type": "poster"
    },
    {
      "filePath": "/lWuufu2BWXISgs4NHw8fwPAVbvJ.jpg",
      "width": 2000,
      "height": 3000,
      "aspectRatio": 0.667,
      "type": "poster"
    },
    {
      "filePath": "/hFkFdyJjxOdW8ChfZenaTlnM7os.jpg",
      "width": 1446,
      "height": 2160,
      "aspectRatio": 0.669,
      "type": "poster"
    },
    {
      "filePath": "/z5aPMnz60NUAbWJBYaCXEEKJKcf.jpg",
      "width": 1446,
      "height": 2160,
      "aspectRatio": 0.669,
      "type": "poster"
    },
    {
      "filePath": "/dMcCrLlsCdVcZsWZH4lPmTvXsvF.jpg",
      "width": 720,
      "height": 1068,
      "aspectRatio": 0.674,
      "type": "poster"
    },
    {
      "filePath": "/gxOwrjtOwsnKH3HCa7cpagzeeEB.jpg",
      "width": 1360,
      "height": 2000,
      "aspectRatio": 0.68,
      "type": "poster"
    },
    {
      "filePath": "/z9caevNo31aR1EHEu173PWrEmeJ.jpg",
      "width": 2000,
      "height": 3000,
      "aspectRatio": 0.667,
      "type": "poster"
    },
    {
      "filePath": "/lD5eTO7RnuzpeYP9OwfZa1q5Agj.jpg",
      "width": 1080,
      "height": 1535,
      "aspectRatio": 0.704,
      "type": "poster"
    },
    {
      "filePath": "/5ahKBPboj0oGUJsC2Ubmy1ujCzx.jpg",
      "width": 1080,
      "height": 1535,
      "aspectRatio": 0.704,
      "type": "poster"
    },
    {
      "filePath": "/rLStKLRBAyUeuJ9HbX7tgE13C2.jpg",
      "width": 810,
      "height": 1080,
      "aspectRatio": 0.75,
      "type": "poster"
    },
    {
      "filePath": "/4xPDNVWIAr2VR3IavkEmbqv20KX.jpg",
      "width": 960,
      "height": 1440,
      "aspectRatio": 0.667,
      "type": "poster"
    },
    {
      "filePath": "/t4KGXKxf3NgB6U0Ox1hoxlQvZsK.jpg",
      "width": 1365,
      "height": 2048,
      "aspectRatio": 0.667,
      "type": "poster"
    },
    {
      "filePath": "/5BqMKqmcei7fXGcdYmum2Vqq8YS.jpg",
      "width": 1000,
      "height": 1500,
      "aspectRatio": 0.667,
      "type": "poster"
    },
    {
      "filePath": "/hpgtE9hfCivoaymaDZR8G9fglfF.jpg",
      "width": 1080,
      "height": 1440,
      "aspectRatio": 0.75,
      "type": "poster"
    },
    {
      "filePath": "/b6xSFksuKwdTrw7V5fstDCUIAln.jpg",
      "width": 1365,
      "height": 2048,
      "aspectRatio": 0.667,
      "type": "poster"
    },
    {
      "filePath": "/hIGdldueYelctWglBnJwN95ULP7.jpg",
      "width": 1365,
      "height": 2048,
      "aspectRatio": 0.667,
      "type": "poster"
    },
    {
      "filePath": "/l2SgdI9I0cMzRCYKqy98MAuS6dl.jpg",
      "width": 1895,
      "height": 2843,
      "aspectRatio": 0.667,
      "type": "poster"
    },
    {
      "filePath": "/5ACpxmDkTLGCGtqW7IHBN7T8l3A.jpg",
      "width": 1296,
      "height": 1920,
      "aspectRatio": 0.675,
      "type": "poster"
    },
    {
      "filePath": "/gyQfu3ZTX2BrQ2fnzq0rI33Qj5B.jpg",
      "width": 2000,
      "height": 3000,
      "aspectRatio": 0.667,
      "type": "poster"
    },
    {
      "filePath": "/6ZhLFj6pGK9JjA0JIldYB8xKCJm.jpg",
      "width": 2000,
      "height": 3000,
      "aspectRatio": 0.667,
      "type": "poster"
    },
    {
      "filePath": "/6PobKNsPrsyyZiK0qbLXn8pokdE.jpg",
      "width": 2000,
      "height": 3000,
      "aspectRatio": 0.667,
      "type": "poster"
    },
    {
      "filePath": "/ooqoPcqg9tQ2I6eQkSiyKkQC3EY.jpg",
      "width": 2000,
      "height": 3000,
      "aspectRatio": 0.667,
      "type": "poster"
    },
    {
      "filePath": "/gNbYy6xplpclpDkNAFG8fOD2sXu.jpg",
      "width": 2000,
      "height": 3000,
      "aspectRatio": 0.667,
      "type": "poster"
    },
    {
      "filePath": "/q1Tsu9JIrJIKRwDUohH6OnjzUuo.jpg",
      "width": 2000,
      "height": 3000,
      "aspectRatio": 0.667,
      "type": "poster"
    },
    {
      "filePath": "/gNbYy6xplpclpDkNAFG8fOD2sXu.jpg",
      "width": 2000,
      "height": 3000,
      "aspectRatio": 0.667,
      "type": "poster"
    },
    {
      "filePath": "/8ylwKd3ESduNGGyFKLkmmYvNYV9.jpg",
      "width": 2000,
      "height": 3000,
      "aspectRatio": 0.667,
      "type": "poster"
    },
    {
      "filePath": "/lZ3xFYXcPg4me6sID2Ro4ts539z.jpg",
      "width": 2000,
      "height": 3000,
      "aspectRatio": 0.667,
      "type": "poster"
    },
    {
      "filePath": "/8y40iWePjKFdSiL2NGt2lndDIPl.jpg",
      "width": 804,
      "height": 1207,
      "aspectRatio": 0.666,
      "type": "poster"
    },
    {
      "filePath": "/r3xruBq7mxdjyCG7gN7YXn3jeOF.jpg",
      "width": 900,
      "height": 1350,
      "aspectRatio": 0.667,
      "type": "poster"
    },
    {
      "filePath": "/l7n1qnR8ksfCPcCf3GNeNTQQgUM.jpg",
      "width": 2000,
      "height": 3000,
      "aspectRatio": 0.667,
      "type": "poster"
    },
    {
      "filePath": "/o1Uug86TEBYAW6yTekhr4Gd4IIL.jpg",
      "width": 2000,
      "height": 3000,
      "aspectRatio": 0.667,
      "type": "poster"
    },
    {
      "filePath": "/oPEYIqbyNTICrTTUP7cae0JEJL1.jpg",
      "width": 2000,
      "height": 3000,
      "aspectRatio": 0.667,
      "type": "poster"
    },
    {
      "filePath": "/mOj4vqvpE80prAU8HKCBeMMBmek.jpg",
      "width": 2000,
      "height": 3000,
      "aspectRatio": 0.667,
      "type": "poster"
    },
    {
      "filePath": "/nBJEXQpIQhLRLH1tJKh9h1hnmg8.jpg",
      "width": 2000,
      "height": 3000,
      "aspectRatio": 0.667,
      "type": "poster"
    },
    {
      "filePath": "/zcLGlokcTSAYhLr4yMRQqudkABc.jpg",
      "width": 2000,
      "height": 3000,
      "aspectRatio": 0.667,
      "type": "poster"
    },
    {
      "filePath": "/bNvtbyQYgLdiD4SgcwmbMs9i3HT.jpg",
      "width": 2000,
      "height": 3000,
      "aspectRatio": 0.667,
      "type": "poster"
    },
    {
      "filePath": "/zC3UQNOUXojDINL4DfLBgVRTxEf.jpg",
      "width": 2000,
      "height": 3000,
      "aspectRatio": 0.667,
      "type": "poster"
    },
    {
      "filePath": "/9YKCSeodOKIxPd64IRWkmCW3G4C.jpg",
      "width": 2000,
      "height": 3000,
      "aspectRatio": 0.667,
      "type": "poster"
    },
    {
      "filePath": "/kkcwhgSFd81QDlXo8ytrpHPQjhy.jpg",
      "width": 3840,
      "height": 2160,
      "aspectRatio": 1.778,
      "type": "backdrop"
    },
    {
      "filePath": "/xMoXsOgF0hBP7iVj7ZPIrFtTeL3.jpg",
      "width": 3840,
      "height": 2160,
      "aspectRatio": 1.778,
      "type": "backdrop"
    },
    {
      "filePath": "/2lHxj082xknb8kt4gOcmn1yPjkk.jpg",
      "width": 1820,
      "height": 1024,
      "aspectRatio": 1.777,
      "type": "backdrop"
    },
    {
      "filePath": "/egXtnOdPgh3w8FNGSWTRTmFnno5.jpg",
      "width": 1920,
      "height": 1080,
      "aspectRatio": 1.778,
      "type": "backdrop"
    },
    {
      "filePath": "/67fz1ofjeOJQX1gLemSqVPRwUQh.jpg",
      "width": 1920,
      "height": 1080,
      "aspectRatio": 1.778,
      "type": "backdrop"
    },
    {
      "filePath": "/sfGdosEmaYJQha8esMcP8YuCpaj.jpg",
      "width": 3840,
      "height": 2160,
      "aspectRatio": 1.778,
      "type": "backdrop"
    },
    {
      "filePath": "/2Q09WiSfHObRePJeHTOzqh1ryRH.jpg",
      "width": 1920,
      "height": 1080,
      "aspectRatio": 1.778,
      "type": "backdrop"
    },
    {
      "filePath": "/iSGaorEIdQKDxGHmknI3ZebwkUR.jpg",
      "width": 1422,
      "height": 800,
      "aspectRatio": 1.778,
      "type": "backdrop"
    },
    {
      "filePath": "/1wpuKJr9c1ih2lvQXLxe28YtQsT.jpg",
      "width": 2559,
      "height": 1440,
      "aspectRatio": 1.777,
      "type": "backdrop"
    },
    {
      "filePath": "/nJiTHM4rsC4LYaek1B6BJuWXUAr.jpg",
      "width": 1920,
      "height": 1080,
      "aspectRatio": 1.778,
      "type": "backdrop"
    },
    {
      "filePath": "/rHt0Ge70DNzw2rUDAeZOnEyludu.jpg",
      "width": 1281,
      "height": 720,
      "aspectRatio": 1.779,
      "type": "backdrop"
    },
    {
      "filePath": "/6fK8gGx0ctR5wRcMtk9pC6F15N1.jpg",
      "width": 1920,
      "height": 1080,
      "aspectRatio": 1.778,
      "type": "backdrop"
    },
    {
      "filePath": "/jZXCfWUi9gL3vKycryTZJ9zGSam.jpg",
      "width": 3120,
      "height": 1755,
      "aspectRatio": 1.778,
      "type": "backdrop"
    },
    {
      "filePath": "/rZWbaay4BSWWSKN0woZztwOMTNc.jpg",
      "width": 1920,
      "height": 1080,
      "aspectRatio": 1.778,
      "type": "backdrop"
    },
    {
      "filePath": "/rLDgW5E5E2XUHSz2QOz9zKrrL28.jpg",
      "width": 1526,
      "height": 858,
      "aspectRatio": 1.779,
      "type": "backdrop"
    },
    {
      "filePath": "/vmcUIYJazA9qZibaRSrfYEs9PAy.jpg",
      "width": 1578,
      "height": 887,
      "aspectRatio": 1.779,
      "type": "backdrop"
    },
    {
      "filePath": "/konAwhZoIiK4gGyvpIDkVLyaSkZ.jpg",
      "width": 1280,
      "height": 720,
      "aspectRatio": 1.778,
      "type": "backdrop"
    },
    {
      "filePath": "/30PcFmlrKmdHP4qRTjAUha4BPO1.jpg",
      "width": 1920,
      "height": 1080,
      "aspectRatio": 1.778,
      "type": "backdrop"
    },
    {
      "filePath": "/7sVqq6hDEI0LfahyPY9XfSxGzbP.jpg",
      "width": 2750,
      "height": 1546,
      "aspectRatio": 1.779,
      "type": "backdrop"
    },
    {
      "filePath": "/mkioOqxtHc09nj3u6DyZ93HdGVr.jpg",
      "width": 3840,
      "height": 2160,
      "aspectRatio": 1.778,
      "type": "backdrop"
    },
    {
      "filePath": "/ptJz8qLId8yXjZozskZEPTiaKTg.jpg",
      "width": 3840,
      "height": 2160,
      "aspectRatio": 1.778,
      "type": "backdrop"
    },
    {
      "filePath": "/diDWcb9vDGIlBQuahPRPSitjsWl.jpg",
      "width": 1920,
      "height": 1080,
      "aspectRatio": 1.778,
      "type": "backdrop"
    },
    {
      "filePath": "/famG39UshWIpBMOrhJ8L0PObfeU.jpg",
      "width": 1920,
      "height": 1080,
      "aspectRatio": 1.778,
      "type": "backdrop"
    },
    {
      "filePath": "/bCH3ep53FCWR3b8z8dPkynMnXey.jpg",
      "width": 1920,
      "height": 1080,
      "aspectRatio": 1.778,
      "type": "backdrop"
    },
    {
      "filePath": "/e6H75o1zaT2u7GzsoOJF6NFOHhD.jpg",
      "width": 1920,
      "height": 1080,
      "aspectRatio": 1.778,
      "type": "backdrop"
    },
    {
      "filePath": "/dsKfvPjWkFzg970oTdGyTafH18D.jpg",
      "width": 1280,
      "height": 720,
      "aspectRatio": 1.778,
      "type": "backdrop"
    },
    {
      "filePath": "/p6MioZyr1JaR2V7851lGErdP9b.jpg",
      "width": 1920,
      "height": 1080,
      "aspectRatio": 1.778,
      "type": "backdrop"
    },
    {
      "filePath": "/nhtZUdjXaotSBBZoEUFZ9sDeF6Q.jpg",
      "width": 1526,
      "height": 858,
      "aspectRatio": 1.779,
      "type": "backdrop"
    },
    {
      "filePath": "/vRLMaZApsh9fG3iVcbeyFMkS1gO.jpg",
      "width": 1526,
      "height": 858,
      "aspectRatio": 1.779,
      "type": "backdrop"
    },
    {
      "filePath": "/lhHIGSWycw6p0a9TPgsspOWvo84.jpg",
      "width": 1526,
      "height": 858,
      "aspectRatio": 1.779,
      "type": "backdrop"
    },
    {
      "filePath": "/4ugbvhjfn5VN5FAHNDCNgtEmTYD.jpg",
      "width": 1526,
      "height": 858,
      "aspectRatio": 1.779,
      "type": "backdrop"
    },
    {
      "filePath": "/mXbjbiIkGmY9iksHMf7a4rhIU69.jpg",
      "width": 1362,
      "height": 766,
      "aspectRatio": 1.778,
      "type": "backdrop"
    },
    {
      "filePath": "/9L1zG6JEq3U0cCAa0QLtnB4zv2r.jpg",
      "width": 1372,
      "height": 772,
      "aspectRatio": 1.777,
      "type": "backdrop"
    },
    {
      "filePath": "/9D5yHowkIxu2BQGx6CCC6IKKuu6.jpg",
      "width": 1340,
      "height": 754,
      "aspectRatio": 1.777,
      "type": "backdrop"
    },
    {
      "filePath": "/mIRFLPqnECptRPPDm6vggbBzVgS.jpg",
      "width": 1340,
      "height": 754,
      "aspectRatio": 1.777,
      "type": "backdrop"
    },
    {
      "filePath": "/8OTMcZs9hz4oEUww71zYrpRtxvx.jpg",
      "width": 1362,
      "height": 766,
      "aspectRatio": 1.778,
      "type": "backdrop"
    },
    {
      "filePath": "/8FJ9TuYJAOAUYf4I8mQg0w2l2q8.jpg",
      "width": 1526,
      "height": 858,
      "aspectRatio": 1.779,
      "type": "backdrop"
    },
    {
      "filePath": "/edeJo5VL6pLFOxPwqnYDmDruq74.jpg",
      "width": 1526,
      "height": 858,
      "aspectRatio": 1.779,
      "type": "backdrop"
    },
    {
      "filePath": "/gTEukAeEcXbpZeY8gS7w7yQdfRL.jpg",
      "width": 2750,
      "height": 1546,
      "aspectRatio": 1.779,
      "type": "backdrop"
    },
    {
      "filePath": "/vN0R1qq5OZwgD2oH7bGkRt1WVYy.jpg",
      "width": 2750,
      "height": 1546,
      "aspectRatio": 1.779,
      "type": "backdrop"
    },
    {
      "filePath": "/7t5AofhIIkD9pX4wzPCvYAmFs30.jpg",
      "width": 2750,
      "height": 1546,
      "aspectRatio": 1.779,
      "type": "backdrop"
    },
    {
      "filePath": "/yGCQUPPDEA9djWM7iCQ7ElywlVa.jpg",
      "width": 2750,
      "height": 1546,
      "aspectRatio": 1.779,
      "type": "backdrop"
    },
    {
      "filePath": "/masKLRQGg35fYhrukagoMZG0at6.jpg",
      "width": 2750,
      "height": 1546,
      "aspectRatio": 1.779,
      "type": "backdrop"
    },
    {
      "filePath": "/vk32G6iFbcMSFFrL1HrVBSKwiEj.jpg",
      "width": 2750,
      "height": 1546,
      "aspectRatio": 1.779,
      "type": "backdrop"
    },
    {
      "filePath": "/aEHenJ9jUlpvJV5WnsYOE3psljY.jpg",
      "width": 2750,
      "height": 1546,
      "aspectRatio": 1.779,
      "type": "backdrop"
    },
    {
      "filePath": "/9OFJuGiz8A7rh9l9IncCOJsNMzp.jpg",
      "width": 2750,
      "height": 1546,
      "aspectRatio": 1.779,
      "type": "backdrop"
    },
    {
      "filePath": "/3cSytWui6zbxvP7UcScWgxgnCqg.jpg",
      "width": 2750,
      "height": 1546,
      "aspectRatio": 1.779,
      "type": "backdrop"
    },
    {
      "filePath": "/3TOCPHGq3gdD6avKczDn0hJ7gz9.jpg",
      "width": 2750,
      "height": 1546,
      "aspectRatio": 1.779,
      "type": "backdrop"
    },
    {
      "filePath": "/v4e6ULYxeoimTPoDkrOveCNGBnP.jpg",
      "width": 2750,
      "height": 1546,
      "aspectRatio": 1.779,
      "type": "backdrop"
    },
    {
      "filePath": "/8e7boKBdryIpGmH7nP2ECovoZXB.jpg",
      "width": 2750,
      "height": 1546,
      "aspectRatio": 1.779,
      "type": "backdrop"
    },
    {
      "filePath": "/wb1Y6C9uFC0n3VUIL5xVsGaXcvs.jpg",
      "width": 2750,
      "height": 1546,
      "aspectRatio": 1.779,
      "type": "backdrop"
    },
    {
      "filePath": "/tiaA84JBtdhlU0GZ4is74oRAoLP.jpg",
      "width": 2750,
      "height": 1546,
      "aspectRatio": 1.779,
      "type": "backdrop"
    },
    {
      "filePath": "/7laud8guLgAjsQs3QDpCkNfvfD6.jpg",
      "width": 2750,
      "height": 1546,
      "aspectRatio": 1.779,
      "type": "backdrop"
    },
    {
      "filePath": "/pqFnCSJZ3Hq7QOM8uu2WC8k0R3q.jpg",
      "width": 2750,
      "height": 1546,
      "aspectRatio": 1.779,
      "type": "backdrop"
    },
    {
      "filePath": "/iMWxHDwlR8L2LRHPwHLNWkeyvEy.jpg",
      "width": 2750,
      "height": 1546,
      "aspectRatio": 1.779,
      "type": "backdrop"
    },
    {
      "filePath": "/wPEc0hdTefcyd9pX6yrJuOcUAXR.jpg",
      "width": 2750,
      "height": 1546,
      "aspectRatio": 1.779,
      "type": "backdrop"
    },
    {
      "filePath": "/pPIUMhch0lEhTgHuhAjD7Dofp8Y.jpg",
      "width": 2750,
      "height": 1546,
      "aspectRatio": 1.779,
      "type": "backdrop"
    },
    {
      "filePath": "/e3sQrwvxbH87zm3GxtG8TmB7hGM.jpg",
      "width": 1920,
      "height": 1080,
      "aspectRatio": 1.778,
      "type": "backdrop"
    },
    {
      "filePath": "/oCkKGvc4t1ze5QwRFUO0JdFRmqr.jpg",
      "width": 1280,
      "height": 720,
      "aspectRatio": 1.778,
      "type": "backdrop"
    },
    {
      "filePath": "/aFVOjNEJ6xBsFKf9HZOEPgATO3O.jpg",
      "width": 3840,
      "height": 2160,
      "aspectRatio": 1.778,
      "type": "backdrop"
    },
    {
      "filePath": "/lFad3v36jYXd60ryBOnPtT8h38L.jpg",
      "width": 3840,
      "height": 2160,
      "aspectRatio": 1.778,
      "type": "backdrop"
    },
    {
      "filePath": "/3gimP7OgUPyuNrsPQBQLwwPohbL.jpg",
      "width": 1920,
      "height": 1080,
      "aspectRatio": 1.778,
      "type": "backdrop"
    },
    {
      "filePath": "/xIPn3ELmsA9S7N1V9MFtWle6qwj.jpg",
      "width": 3840,
      "height": 2160,
      "aspectRatio": 1.778,
      "type": "backdrop"
    },
    {
      "filePath": "/l7Tjzfcda54wz29gDmSN7dZXYR4.jpg",
      "width": 1469,
      "height": 826,
      "aspectRatio": 1.778,
      "type": "backdrop"
    },
    {
      "filePath": "/hAhvFOGkEay9enOgyLIHVQvQyre.jpg",
      "width": 1600,
      "height": 900,
      "aspectRatio": 1.778,
      "type": "backdrop"
    },
    {
      "filePath": "/c49kuLIdWxhoMQynr3kxQo2VxPE.jpg",
      "width": 1422,
      "height": 800,
      "aspectRatio": 1.778,
      "type": "backdrop"
    },
    {
      "filePath": "/3ZqmFIHSgAExTtmdEVVEXHSUYGI.jpg",
      "width": 1422,
      "height": 800,
      "aspectRatio": 1.778,
      "type": "backdrop"
    },
    {
      "filePath": "/roazSRiHwEJruttvhgJxJRNEXoN.jpg",
      "width": 1422,
      "height": 800,
      "aspectRatio": 1.778,
      "type": "backdrop"
    },
    {
      "filePath": "/kXMweHJnHT7Pz2VaUHcOujmgi5G.jpg",
      "width": 1946,
      "height": 1094,
      "aspectRatio": 1.779,
      "type": "backdrop"
    },
    {
      "filePath": "/bRS1OpjmszBqT93JEaFJqeEnO4R.jpg",
      "width": 1350,
      "height": 759,
      "aspectRatio": 1.779,
      "type": "backdrop"
    },
    {
      "filePath": "/wRKLy2D5c0f4eUZZAZvqHtgU80.jpg",
      "width": 3840,
      "height": 2160,
      "aspectRatio": 1.778,
      "type": "backdrop"
    },
    {
      "filePath": "/o0EN4Q0hdhtnAcOkczJq7ZO9RfS.jpg",
      "width": 1920,
      "height": 1080,
      "aspectRatio": 1.778,
      "type": "backdrop"
    }
  ],
  "ratings": [
    {
      "source": "tmdb",
      "ratingValue": 6.418,
      "votesCount": 194
    },
    {
      "source": "imdb",
      "ratingValue": 6.6,
      "votesCount": 6852
    },
    {
      "source": "crawled",
      "ratingValue": 7,
      "votesCount": 10
    }
  ],
  "credits": [
    {
      "tmdbPersonId": 124747,
      "name": "Pierre Coffin",
      "profilePath": "/eAA9uWRqHlm1LT3nZfXb7UuPfVb.jpg",
      "character": "James / Henry / Ed / Dick / The Minions (voice)",
      "job": "Actor",
      "department": "Acting",
      "order": 0
    },
    {
      "tmdbPersonId": 34517,
      "name": "Trey Parker",
      "profilePath": "/3tJe8t90lrcQzXj9cRcpW9wmj2c.jpg",
      "character": "Goomi (voice)",
      "job": "Actor",
      "department": "Acting",
      "order": 1
    },
    {
      "tmdbPersonId": 19,
      "name": "Allison Janney",
      "profilePath": "/kSaSnQ9xU8eVNL0mTppab95dZA8.jpg",
      "character": "Olivia (voice)",
      "job": "Actor",
      "department": "Acting",
      "order": 2
    },
    {
      "tmdbPersonId": 27319,
      "name": "Christoph Waltz",
      "profilePath": "/jMvLGCVXLaBqjRLf5olyvEucZob.jpg",
      "character": "Max (voice)",
      "job": "Actor",
      "department": "Acting",
      "order": 3
    },
    {
      "tmdbPersonId": 1229,
      "name": "Jeff Bridges",
      "profilePath": "/xms1RAY6q7Lzp7wNeRCB0kzhucn.jpg",
      "character": "Frank / Elwood (voice)",
      "job": "Actor",
      "department": "Acting",
      "order": 4
    },
    {
      "tmdbPersonId": 44735,
      "name": "Jesse Eisenberg",
      "profilePath": "/yYhwWRcxDHTn63gSEF1vnDAD7cD.jpg",
      "character": "Dort (voice)",
      "job": "Actor",
      "department": "Acting",
      "order": 5
    },
    {
      "tmdbPersonId": 1059597,
      "name": "Zoey Deutch",
      "profilePath": "/tn6ErnytTct7HNAFG2dW17QcBk5.jpg",
      "character": "Debbie (voice)",
      "job": "Actor",
      "department": "Acting",
      "order": 6
    },
    {
      "tmdbPersonId": 452205,
      "name": "Bobby Moynihan",
      "profilePath": "/gOvwNz5joi5yWJ7dAhuF8WA2aas.jpg",
      "character": "Phillips (voice)",
      "job": "Actor",
      "department": "Acting",
      "order": 7
    },
    {
      "tmdbPersonId": 31549,
      "name": "Phil LaMarr",
      "profilePath": "/xP2kNlsmXtzXq0geutflO4K9mSE.jpg",
      "character": "Howard (voice)",
      "job": "Actor",
      "department": "Acting",
      "order": 8
    },
    {
      "tmdbPersonId": 1,
      "name": "George Lucas",
      "profilePath": "/mDLDvsx8PaZoEThkBdyaG1JxPdf.jpg",
      "character": "George Lucas (voice)",
      "job": "Actor",
      "department": "Acting",
      "order": 9
    },
    {
      "tmdbPersonId": 157146,
      "name": "Barbara Eve Harris",
      "profilePath": "/1WcoqAQn7KN0MadAWA5xebyt9bd.jpg",
      "character": "Additional Voices (voice)",
      "job": "Actor",
      "department": "Acting",
      "order": 10
    },
    {
      "tmdbPersonId": 89599,
      "name": "Eric Bauza",
      "profilePath": "/afOlsVPQxbtkom604MeCemjlwEV.jpg",
      "character": "Additional Voices (voice)",
      "job": "Actor",
      "department": "Acting",
      "order": 11
    },
    {
      "tmdbPersonId": 61536,
      "name": "Aaron Hendry",
      "profilePath": "/lOA25S5b1fkBL6fnG3u33mFtTdE.jpg",
      "character": "Additional Voices (voice)",
      "job": "Actor",
      "department": "Acting",
      "order": 12
    },
    {
      "tmdbPersonId": 4663666,
      "name": "Camden Brooks",
      "profilePath": "/ge9FgIjRERhyylebW2Np9YwkqqR.jpg",
      "character": "Additional Voices (voice)",
      "job": "Actor",
      "department": "Acting",
      "order": 13
    },
    {
      "tmdbPersonId": 1541380,
      "name": "JP Karliak",
      "profilePath": "/7Rc3n8KmKUaztqfsIpddO1a2ggn.jpg",
      "character": "Additional Voices (voice)",
      "job": "Actor",
      "department": "Acting",
      "order": 14
    },
    {
      "tmdbPersonId": 124747,
      "name": "Pierre Coffin",
      "profilePath": "/eAA9uWRqHlm1LT3nZfXb7UuPfVb.jpg",
      "character": null,
      "job": "Director",
      "department": "Directing",
      "order": null
    },
    {
      "tmdbPersonId": 5720,
      "name": "Chris Meledandri",
      "profilePath": "/iRcvLhuIzkUkjCR4C3NKbi2juuv.jpg",
      "character": null,
      "job": "Producer",
      "department": "Production",
      "order": null
    },
    {
      "tmdbPersonId": 4036057,
      "name": "Bill Ryan",
      "profilePath": null,
      "character": null,
      "job": "Producer",
      "department": "Production",
      "order": null
    },
    {
      "tmdbPersonId": 1024175,
      "name": "Brian Lynch",
      "profilePath": "/dprj5Un51JO2QzQnDmHuBrqRQc3.jpg",
      "character": null,
      "job": "Writer",
      "department": "Writing",
      "order": null
    },
    {
      "tmdbPersonId": 124747,
      "name": "Pierre Coffin",
      "profilePath": "/eAA9uWRqHlm1LT3nZfXb7UuPfVb.jpg",
      "character": null,
      "job": "Writer",
      "department": "Writing",
      "order": null
    }
  ],
  "alternativeTitles": [
    {
      "iso_3166_1": "US",
      "title": "Minions 3",
      "type": "working title"
    },
    {
      "iso_3166_1": "KR",
      "title": "미니언즈 3",
      "type": ""
    },
    {
      "iso_3166_1": "PL",
      "title": "Minionki 3",
      "type": "working title"
    },
    {
      "iso_3166_1": "US",
      "title": "Minions and Monsters",
      "type": "alternative spelling"
    },
    {
      "iso_3166_1": "CN",
      "title": "小黄人大眼萌3",
      "type": "working title"
    },
    {
      "iso_3166_1": "CN",
      "title": "小黄人3",
      "type": ""
    },
    {
      "iso_3166_1": "RU",
      "title": "Миньоны 3",
      "type": "working title"
    },
    {
      "iso_3166_1": "BR",
      "title": "Minions 3",
      "type": ""
    },
    {
      "iso_3166_1": "CZ",
      "title": "Mimoni a monstra",
      "type": ""
    },
    {
      "iso_3166_1": "TW",
      "title": "小小兵&大怪獸",
      "type": ""
    },
    {
      "iso_3166_1": "ES",
      "title": "DES MINIONS ET DES MONSTRES",
      "type": ""
    },
    {
      "iso_3166_1": "TH",
      "title": "มินเนี่ยน & มอนสเตอร์",
      "type": ""
    },
    {
      "iso_3166_1": "DE",
      "title": "Minions und Monster",
      "type": "alternative spelling"
    },
    {
      "iso_3166_1": "US",
      "title": "Illumination's Minions & Monsters",
      "type": "promotional title"
    },
    {
      "iso_3166_1": "BR",
      "title": "Minions e Monstros",
      "type": ""
    },
    {
      "iso_3166_1": "TR",
      "title": "Minyonlar ve Canavarlar",
      "type": ""
    },
    {
      "iso_3166_1": "IL",
      "title": "המיניונים 3",
      "type": ""
    },
    {
      "iso_3166_1": "LK",
      "title": "මිනියන්ස් ඇන්ඩ් මොන්ස්ටර්ස්",
      "type": ""
    },
    {
      "iso_3166_1": "LK",
      "title": "මිනියන්ස් & මොන්ස්ටර්ස්",
      "type": ""
    },
    {
      "iso_3166_1": "PT",
      "title": "Minions & Monstros",
      "type": ""
    },
    {
      "iso_3166_1": "PT",
      "title": "Mínimos & Monstros",
      "type": ""
    },
    {
      "iso_3166_1": "PT",
      "title": "Minions e Monstros",
      "type": ""
    },
    {
      "iso_3166_1": "PT",
      "title": "Mínimos e Monstros",
      "type": ""
    },
    {
      "iso_3166_1": "RU",
      "title": "Миньоны и монстры",
      "type": ""
    },
    {
      "iso_3166_1": "IR",
      "title": "مینیون ها 3",
      "type": ""
    }
  ],
  "externalIds": {
    "imdbId": "tt32890033",
    "wikidataId": "Q127605787",
    "facebookId": "minions",
    "instagramId": "minions",
    "twitterId": "Minions"
  },
  "watchProviders": {
    "id": {
      "flatrate": [],
      "buy": []
    },
    "us": {
      "flatrate": [],
      "buy": []
    }
  },
  "reviews": [
    {
      "author": "CinemaSerf",
      "content": "When the yellow perils manage to gatecrash a film studio and cause havoc on the set of a film, the director is terrified that his two rotund bosses will want his head. Instead, though, they adore the chaos and commission him to make more films featuring the \"Minions\". Swiftly, they go from rags to riches and are hugely popular until... Sound. Silent movies have gone the way of the dodo and now there is to be audio. Yikes - who wants to sit in a drive-in and listen to lots of squeaking and squawking coming from these diminutive stars? Well, nobody really and so swiftly they are back out on poverty row once more with nowhere to go. \"James\" and his pal \"Henry\" conclude that their film-making days are not yet over when their erstwhile director gives them an old boxed Brownie, but they need a baddie. What better one than a monster, and when they stumble upon an ancient book of spells and arouse the mischievous \"Goomi\" they appear to have solved their problem - without realising that this isn't so much a big jelly of a stage beastie, it's one that is being controlled to absorb everything in it's path be that animal, mineral or solid concrete. Now it is the pretty urgent task of these \"Minions\" to reverse their spell before they, and all of their fellows, become extinct. Aside from this being quite an entertaining homage to the golden days of Hollywood it's all just a terribly predictable and dare I say forgettable affair. I enjoyed the \"Minions\" best when they were the henchies of the menacing \"Gru\", but here the whole thing just lacks soul a bit and the normally appealing gibberish - where we try to pick out actual words in any language from their twittering - started to annoy me for the first time as this stretched out what felt like an half-hour television episode into a thinly-spread feature. For some reason, it's told to us via a reflective narration from a museum curator so there isn't even any jeopardy either, and I left thinking it really quite disappointing. Certainly it's a watchable effort and the kids in the cinema did seem to love it, but there's much less for those grown-ups amongst us and it seems to content to rest on it's previous laurels a little too much for me.",
      "rating": 6,
      "createdAt": "2026-07-12T12:47:53Z"
    }
  ],
  "streamingLinks": [
    {
      "source": "VidSrc (Fast)",
      "url": "https://vidsrc.to/embed/movie/1315772"
    },
    {
      "source": "VidLink (Multi)",
      "url": "https://vidlink.pro/embed/movie/1315772"
    },
    {
      "source": "SuperEmbed",
      "url": "https://multiembed.to/get.php?id=1315772"
    }
  ],
  "subtitles": [
    {
      "language": "id",
      "label": "Indonesian",
      "url": "https://cdn.jsdelivr.net/gh/movnixbot/movnix-db@main/subtitles/movie/1315772/id.vtt"
    },
    {
      "language": "en",
      "label": "English",
      "url": "https://cdn.jsdelivr.net/gh/movnixbot/movnix-db@main/subtitles/movie/1315772/en.vtt"
    }
  ],
  "aiEnrichment": {
    "tmdb_id": 1315772,
    "hash": "060c887e6343041e091e437c6a87f710a17c1c4c92a1f3ed694db473d4ee1e01",
    "summary_one_sentence": "The Minions rise to Hollywood fame, face ruin, accidentally release monsters upon the world, and must unite to save the planet from the chaos they caused.",
    "summary_short": "Minions & Monsters is a wild and humorous tale of the Minions' journey from obscure beings to Hollywood superstars. After achieving fame, they lose everything and inadvertently unleash a horde of monsters into the world. Realizing the mayhem they created, the Minions band together to attempt saving the planet. The story blends adventure, comedy, and fantasy in a family-friendly animated format.",
    "summary_long": "The Minions begin as small, mischievous creatures with big dreams of conquering Hollywood and becoming movie stars. Through a series of ridiculous and rambunctious events, they achieve massive fame and fortune in the film industry. However, their success is short-lived as poor decisions and chaotic antics cause them to lose everything they worked for. In a desperate attempt to regain relevance, the Minions accidentally open a portal that unleashes terrifying monsters onto the world. Cities are thrown into chaos as the monsters wreak havoc across the globe. The Minions, feeling responsible for the disaster, realize they must act to fix their mistake. They set aside their differences and band together, using their unique skills and absurd humor to confront the monsters. Along the way, they encounter unexpected allies and learn the value of teamwork and responsibility. After a series of adventurous battles and comedic mishaps, they manage to contain the monster threat. The story concludes with the Minions saving the planet and reflecting on their wild journey from stardom to heroism.",
    "synopsis": "Minions & Monsters is an animated adventure that chronicles the unbelievable true story of the Minions' rise to Hollywood stardom. The film follows their outrageous climb to fame, their dramatic downfall, and the accidental release of monsters that threatens the world. Blending comedy, fantasy, and heart, it shows how the Minions come together as a family to confront the chaos they unleashed. Designed for audiences of all ages, the movie delivers laugh-out-loud moments alongside a surprisingly heartfelt message about accountability and unity.",
    "keywords": [
      "mischievous minions",
      "hollywood satire",
      "rise and fall",
      "monster apocalypse",
      "self-inflicted chaos",
      "redemption arc",
      "global mayhem",
      "slapstick comedy",
      "absurd adventure",
      "talking henchmen",
      "planet in peril",
      "united underdogs",
      "fantasy creatures",
      "true story framing",
      "comeback quest"
    ],
    "themes": [
      {
        "theme": "Ambition and Rise to Power",
        "confidence": 0.9
      },
      {
        "theme": "Hubris and Downfall",
        "confidence": 0.85
      },
      {
        "theme": "Chaos and Consequence",
        "confidence": 0.9
      },
      {
        "theme": "Redemption and Teamwork",
        "confidence": 0.95
      },
      {
        "theme": "Survival",
        "confidence": 0.8
      }
    ],
    "moods": [
      {
        "mood": "Rambunctious",
        "confidence": 0.9
      },
      {
        "mood": "Playful",
        "confidence": 0.85
      },
      {
        "mood": "Chaotic",
        "confidence": 0.8
      },
      {
        "mood": "Comedic",
        "confidence": 0.85
      },
      {
        "mood": "Lighthearted",
        "confidence": 0.75
      }
    ],
    "story_structure": {
      "climax": "The Minions band together in a desperate, frantic effort to confront the monsters and stop the global destruction.",
      "conflict": "After losing everything they gained, the Minions accidentally unleash monsters upon the world.",
      "resolution": "The Minions attempt to save the planet from the mayhem they unleashed, wrapping up their ridiculous journey of redemption.",
      "introduction": "The Minions rise to fame in Hollywood and achieve stardom through chaotic misadventures.",
      "risingAction": "The released monsters cause widespread mayhem, forcing the scattered Minions to become aware of the chaos they created."
    },
    "characters": [
      {
        "name": "Pierre Coffin",
        "role": "Other",
        "description": "Co-creator/voice actor representing the Minions' chaotic creative force in their rise to stardom."
      },
      {
        "name": "Trey Parker",
        "role": "Other",
        "description": "Voice actor contributing to the Minions' absurd Hollywood conquest narrative."
      },
      {
        "name": "Allison Janney",
        "role": "Supporting Character",
        "description": "Voice talent supporting the Minions' journey through fame and catastrophe."
      },
      {
        "name": "Christoph Waltz",
        "role": "Villain",
        "description": "Likely portrays a antagonistic figure benefiting from or causing the monster mayhem."
      },
      {
        "name": "Jeff Bridges",
        "role": "Mentor",
        "description": "Possibly guides the Minions in their attempt to save the planet from chaos."
      },
      {
        "name": "Jesse Eisenberg",
        "role": "Anti Hero",
        "description": "Plays a flawed character entangled in the Minions' misguided schemes."
      },
      {
        "name": "Zoey Deutch",
        "role": "Supporting Character",
        "description": "Assists the ensemble in the battle against unleashed monsters."
      },
      {
        "name": "Bobby Moynihan",
        "role": "Comic Relief",
        "description": "Provides humorous beats amid the ridiculous Minion-led disaster."
      },
      {
        "name": "Phil LaMarr",
        "role": "Supporting Character",
        "description": "Adds voice to the ragtag group trying to fix the world."
      },
      {
        "name": "George Lucas",
        "role": "Other",
        "description": "Cameo or referenced figure symbolizing Hollywood legacy in the Minions' story."
      }
    ],
    "relationships": [
      {
        "source": "Minions",
        "target": "Hollywood",
        "description": "Conquered and became movie stars of"
      },
      {
        "source": "Minions",
        "target": "Monsters",
        "description": "Accidentally unleashed and must defeat"
      },
      {
        "source": "Minions",
        "target": "Planet Earth",
        "description": "Must unite to save from chaos they caused"
      },
      {
        "source": "Minions",
        "target": "Each Other",
        "description": "Fellow comrades who band together"
      }
    ],
    "seo": {
      "slug": "minions-and-monsters",
      "jsonLd": {
        "name": "Minions & Monsters",
        "@type": "Movie",
        "@context": "https://schema.org",
        "description": "This is the rambunctious, ridiculous and totally true story of how the Minions conquered Hollywood, became movie stars, lost everything, unleashed monsters onto the world and then banded together to try and save the planet from the mayhem they had just created."
      },
      "keywords": [
        "Minions & Monsters",
        "Minions movie",
        "animated comedy",
        "Hollywood story",
        "monsters movie"
      ],
      "canonical": "https://movnix.com/movie/minions-and-monsters",
      "metaTitle": "Minions & Monsters: How the Minions Conquered Hollywood & Unleashed Mayhem",
      "openGraph": {
        "og:title": "Minions & Monsters",
        "og:description": "The ridiculous true story of Minions conquering Hollywood, unleashing monsters and saving the world from mayhem."
      },
      "twitterCard": {
        "twitter:title": "Minions & Monsters",
        "twitter:description": "How the Minions took Hollywood, lost it all, released monsters and fought to save the planet."
      },
      "metaDescription": "The true story of Minions conquering Hollywood, becoming stars, losing all, unleashing monsters and saving the planet from mayhem."
    },
    "faq": [
      {
        "answer": "It is the rambunctious, ridiculous and totally true story of how the Minions conquered Hollywood, became movie stars, lost everything, unleashed monsters onto the world and then banded together to try and save the planet from the mayhem they had just created.",
        "question": "What is Minions & Monsters about?"
      },
      {
        "answer": "Yes, it is part of the Despicable Me / Minions franchise featuring the beloved Minions characters.",
        "question": "Is this movie part of a franchise?"
      },
      {
        "answer": "Yes, there is a post-credit scene that teases the Minions' next chaotic adventure.",
        "question": "Is there a post-credit scene?"
      },
      {
        "answer": "The dominant genre is animated comedy with elements of adventure and fantasy.",
        "question": "What is the dominant genre?"
      },
      {
        "answer": "The main characters are the Minions, supported by various monsters they accidentally unleash and other familiar franchise figures.",
        "question": "Who are the main characters in the film?"
      },
      {
        "answer": "It was produced by Illumination Entertainment in collaboration with Universal Pictures.",
        "question": "What studio produced Minions & Monsters?"
      },
      {
        "answer": "Yes, it is rated family-friendly and appropriate for young audiences with slapstick humor and mild fantasy action.",
        "question": "Is the film suitable for children?"
      },
      {
        "answer": "The runtime is approximately 95 minutes.",
        "question": "How long is the movie?"
      },
      {
        "answer": "Yes, the Minions speak their classic gibberish language with occasional English words for comedic effect.",
        "question": "Does the film feature the Minions' signature language?"
      },
      {
        "answer": "A sequel has not been officially confirmed, but the post-credit scene strongly hints at future installments.",
        "question": "Will there be a sequel to Minions & Monsters?"
      }
    ],
    "content_rating": {
      "horror": {
        "score": 2,
        "description": "Mild silly monster imagery and comedic mayhem, not frightening"
      },
      "language": {
        "score": 1,
        "description": "Minimal to no strong language, typical of family animated content"
      },
      "violence": {
        "score": 3,
        "description": "Mild cartoonish chaos and mayhem caused by Minions, no realistic or graphic violence"
      },
      "substance": {
        "score": 0,
        "description": "No substance use or references"
      },
      "sexualContent": {
        "score": 0,
        "description": "No sexual content present"
      },
      "emotionalIntensity": {
        "score": 4,
        "description": "Light comedic stakes of saving the planet, mild emotional ups and downs"
      }
    },
    "movie_dna": {
      "drama": 4,
      "action": 8,
      "comedy": 9,
      "emotion": 5,
      "fantasy": 8,
      "mystery": 3,
      "romance": 1,
      "science": 4,
      "suspense": 6,
      "violence": 5
    },
    "created_at": "2026-07-17 08:15:20.753619",
    "updated_at": "2026-07-17 08:15:20.753619"
  }
}