{
  "movie": {
    "tmdbId": 1656220,
    "imdbId": "tt41983440",
    "title": "23 000 Lives",
    "originalTitle": "23 000 Leben",
    "overview": "Unable to stand by and watch as countless refugees lose their lives attempting to reach Europe by sea, a group of young Berliners take action. Inexperienced but driven by passion and courage, they launch a crowdfunding campaign to buy an old ship. Venturing into the Mediterranean, they embark on a mission to save thousands of people. But their efforts soon put their understanding of law and justice to the test.",
    "releaseDate": "2026-07-02",
    "runtime": 139,
    "budget": null,
    "revenue": null,
    "status": "Released",
    "popularity": 2.5717,
    "voteAverage": 5,
    "voteCount": 1,
    "homepage": "https://mock-movie-website.com/movies/1656220",
    "posterPath": "/yHIuR7rTAbHXbELc9UqoaOIxXZx.jpg",
    "backdropPath": "/q5L3aXchoCgwbZbwWl5FjhGmuYs.jpg",
    "collectionId": null
  },
  "collection": null,
  "genres": [
    {
      "tmdbId": 18,
      "name": "Drama"
    },
    {
      "tmdbId": 1,
      "name": "Drama"
    }
  ],
  "companies": [
    {
      "tmdbId": 275894,
      "name": "Flimmer",
      "logoPath": "/qKkCZPsYNB3Fbg3TYA2w9BrZQCu.png",
      "originCountry": "DE"
    },
    {
      "tmdbId": 169950,
      "name": "Flute Film",
      "logoPath": "/bnM4d5btAZPCQKU08hm4p6eEMbZ.png",
      "originCountry": "DE"
    },
    {
      "tmdbId": 127981,
      "name": "Sunnysideup Filmproduktion",
      "logoPath": null,
      "originCountry": "DE"
    }
  ],
  "keywords": [],
  "videos": [],
  "images": [
    {
      "filePath": "/yHIuR7rTAbHXbELc9UqoaOIxXZx.jpg",
      "width": null,
      "height": null,
      "aspectRatio": null,
      "type": "poster"
    },
    {
      "filePath": "/q5L3aXchoCgwbZbwWl5FjhGmuYs.jpg",
      "width": null,
      "height": null,
      "aspectRatio": null,
      "type": "backdrop"
    },
    {
      "filePath": "/8ZPoxkREjC92rGIOm2jwWMugl3g.jpg",
      "width": 1417,
      "height": 2001,
      "aspectRatio": 0.708,
      "type": "poster"
    },
    {
      "filePath": "/3hFZwYDgpQbn1zBSmZX6mV0GwzM.jpg",
      "width": 882,
      "height": 1325,
      "aspectRatio": 0.666,
      "type": "poster"
    },
    {
      "filePath": "/gzCzdJB2WwIqUUu3H1NbhL4x636.jpg",
      "width": 2000,
      "height": 3000,
      "aspectRatio": 0.667,
      "type": "poster"
    },
    {
      "filePath": "/6NetwGDaoulIrdwvfbdo0SMi7fz.jpg",
      "width": 1476,
      "height": 2197,
      "aspectRatio": 0.672,
      "type": "poster"
    },
    {
      "filePath": "/q5L3aXchoCgwbZbwWl5FjhGmuYs.jpg",
      "width": 2560,
      "height": 1440,
      "aspectRatio": 1.778,
      "type": "backdrop"
    },
    {
      "filePath": "/oTyJesfUirEVhn2VH9AxIEC8o9U.jpg",
      "width": 1707,
      "height": 960,
      "aspectRatio": 1.778,
      "type": "backdrop"
    },
    {
      "filePath": "/niVh0jiqgnnayXO5tXmACXGESjB.jpg",
      "width": 1280,
      "height": 720,
      "aspectRatio": 1.778,
      "type": "backdrop"
    }
  ],
  "ratings": [
    {
      "source": "tmdb",
      "ratingValue": 5,
      "votesCount": 1
    },
    {
      "source": "crawled",
      "ratingValue": 7,
      "votesCount": 10
    }
  ],
  "credits": [
    {
      "tmdbPersonId": 1037348,
      "name": "Louis Hofmann",
      "profilePath": "/m3Mo38afbKmy9EOsfmUagvTFM9q.jpg",
      "character": null,
      "job": "Actor",
      "department": "Acting",
      "order": 0
    },
    {
      "tmdbPersonId": 1327555,
      "name": "Mala Emde",
      "profilePath": "/rXmhczHGMiN0bhlqTP4qAfoszZL.jpg",
      "character": null,
      "job": "Actor",
      "department": "Acting",
      "order": 1
    },
    {
      "tmdbPersonId": 1682097,
      "name": "Katharina Stark",
      "profilePath": "/3cwKbMriYdDDhPwSQTXTdMhG6p6.jpg",
      "character": null,
      "job": "Actor",
      "department": "Acting",
      "order": 2
    },
    {
      "tmdbPersonId": 49767,
      "name": "Frederick Lau",
      "profilePath": "/4ukrX8OPPsD06YMFoTL00uZrwa4.jpg",
      "character": null,
      "job": "Actor",
      "department": "Acting",
      "order": 3
    },
    {
      "tmdbPersonId": 39249,
      "name": "Maria Dragus",
      "profilePath": "/4AiU1EdwWlNuxBbYV1qLxc09mv1.jpg",
      "character": null,
      "job": "Actor",
      "department": "Acting",
      "order": 4
    },
    {
      "tmdbPersonId": 4114135,
      "name": "Trevor Magaya",
      "profilePath": null,
      "character": null,
      "job": "Actor",
      "department": "Acting",
      "order": 5
    },
    {
      "tmdbPersonId": 5727482,
      "name": "Kathy Etoa",
      "profilePath": "/hIxRBgZbZ4iRTjhVOfvkD8xLB0v.jpg",
      "character": null,
      "job": "Actor",
      "department": "Acting",
      "order": 6
    },
    {
      "tmdbPersonId": 3736493,
      "name": "Saibon Wang",
      "profilePath": null,
      "character": null,
      "job": "Actor",
      "department": "Acting",
      "order": 7
    },
    {
      "tmdbPersonId": 4379940,
      "name": "Joone Dankou",
      "profilePath": null,
      "character": null,
      "job": "Actor",
      "department": "Acting",
      "order": 8
    },
    {
      "tmdbPersonId": 5657421,
      "name": "Merlin Von Garnier",
      "profilePath": "/rBkMLk8mZiMdZ45ox36z8hSO8BG.jpg",
      "character": null,
      "job": "Actor",
      "department": "Acting",
      "order": 9
    },
    {
      "tmdbPersonId": 1658379,
      "name": "Luisa-Céline Gaffron",
      "profilePath": "/tOf2gUN32v2vzngjf2GwKzfpsJ9.jpg",
      "character": null,
      "job": "Actor",
      "department": "Acting",
      "order": 10
    },
    {
      "tmdbPersonId": 2462760,
      "name": "Omid Memar",
      "profilePath": "/bVrmcIOFeyizJ2UyBG7fzNa7NP.jpg",
      "character": null,
      "job": "Actor",
      "department": "Acting",
      "order": 11
    },
    {
      "tmdbPersonId": 680,
      "name": "Corinna Harfouch",
      "profilePath": "/vPs5o94S0as2VSnj4JSATnNTmZa.jpg",
      "character": null,
      "job": "Actor",
      "department": "Acting",
      "order": 12
    },
    {
      "tmdbPersonId": 8796,
      "name": "Ulrich Matthes",
      "profilePath": "/wghkMqyMfaK1yWzwi142LJiJnBM.jpg",
      "character": null,
      "job": "Actor",
      "department": "Acting",
      "order": 13
    },
    {
      "tmdbPersonId": 679,
      "name": "Franka Potente",
      "profilePath": "/aU6f9UemZsTkqKEG4l77zf6masg.jpg",
      "character": null,
      "job": "Actor",
      "department": "Acting",
      "order": 14
    },
    {
      "tmdbPersonId": 37709,
      "name": "Oliver Ziegenbalg",
      "profilePath": null,
      "character": null,
      "job": "Writer",
      "department": "Writing",
      "order": null
    },
    {
      "tmdbPersonId": 2086739,
      "name": "Michele Cinque",
      "profilePath": "/yBDjcjdb4uusuZj1bQ8olgKiMU9.jpg",
      "character": null,
      "job": "Writer",
      "department": "Writing",
      "order": null
    },
    {
      "tmdbPersonId": 37709,
      "name": "Oliver Ziegenbalg",
      "profilePath": null,
      "character": null,
      "job": "Producer",
      "department": "Production",
      "order": null
    },
    {
      "tmdbPersonId": 114001,
      "name": "Markus Goller",
      "profilePath": "/p3BN6OeJU1AntDQ2cbSJEvGgDO7.jpg",
      "character": null,
      "job": "Producer",
      "department": "Production",
      "order": null
    },
    {
      "tmdbPersonId": 114001,
      "name": "Markus Goller",
      "profilePath": "/p3BN6OeJU1AntDQ2cbSJEvGgDO7.jpg",
      "character": null,
      "job": "Director",
      "department": "Directing",
      "order": null
    },
    {
      "tmdbPersonId": 543314,
      "name": "Christopher Zwickler",
      "profilePath": null,
      "character": null,
      "job": "Producer",
      "department": "Production",
      "order": null
    }
  ],
  "alternativeTitles": [],
  "externalIds": {
    "imdbId": "tt41983440",
    "wikidataId": "Q140420253",
    "facebookId": null,
    "instagramId": null,
    "twitterId": null
  },
  "watchProviders": {
    "id": {
      "flatrate": [],
      "buy": []
    },
    "us": {
      "flatrate": [],
      "buy": []
    }
  },
  "reviews": [],
  "streamingLinks": [
    {
      "source": "VidSrc (Fast)",
      "url": "https://vidsrc.to/embed/movie/1656220"
    },
    {
      "source": "VidLink (Multi)",
      "url": "https://vidlink.pro/embed/movie/1656220"
    },
    {
      "source": "SuperEmbed",
      "url": "https://multiembed.to/get.php?id=1656220"
    }
  ],
  "subtitles": [
    {
      "language": "id",
      "label": "Indonesian",
      "url": "https://cdn.jsdelivr.net/gh/movnixbot/movnix-db@main/subtitles/movie/1656220/id.vtt"
    },
    {
      "language": "en",
      "label": "English",
      "url": "https://cdn.jsdelivr.net/gh/movnixbot/movnix-db@main/subtitles/movie/1656220/en.vtt"
    }
  ]
}